kodman/__init__.py
kodman/__main__.py
kodman/_version.py
kodman/backend.py
kodman/engine.py
kodman/utilities.py
kodman-1.1.0.dist-info/licenses/LICENSE
kodman-1.1.0.dist-info/METADATA
kodman-1.1.0.dist-info/WHEEL
kodman-1.1.0.dist-info/entry_points.txt
kodman-1.1.0.dist-info/top_level.txt
kodman-1.1.0.dist-info/RECORD
